mcaptcha_api/__init__.py
mcaptcha_api/client.py
mcaptcha_api-0.1.0.dist-info/METADATA
mcaptcha_api-0.1.0.dist-info/WHEEL
mcaptcha_api-0.1.0.dist-info/RECORD
