Metadata-Version: 2.1
Name: mcaptcha_api
Version: 0.1.0
Summary: A library to interact with mCaptcha API
Project-URL: Homepage, https://git.batsense.net/mCaptcha/mcaptcha-api-py
Project-URL: Issues, https://git.batsense.net/mCaptcha/mcaptcha-api-py/issues
Author-email: Aravinth Manivannan <realaravinth@batsense.net>
Classifier: License :: OSI Approved :: MIT License
Classifier: Operating System :: OS Independent
Classifier: Programming Language :: Python :: 3
Requires-Dist: requests==2.31.0
Requires-Dist: urllib3==2.1.0
